digitalsreeni_image_annotator/__init__.py
digitalsreeni_image_annotator/annotation_statistics.py
digitalsreeni_image_annotator/annotation_utils.py
digitalsreeni_image_annotator/annotator_window.py
digitalsreeni_image_annotator/coco_json_combiner.py
digitalsreeni_image_annotator/constants.py
digitalsreeni_image_annotator/dataset_splitter.py
digitalsreeni_image_annotator/default_stylesheet.py
digitalsreeni_image_annotator/dicom_converter.py
digitalsreeni_image_annotator/export_formats.py
digitalsreeni_image_annotator/help_window.py
digitalsreeni_image_annotator/image_augmenter.py
digitalsreeni_image_annotator/image_label.py
digitalsreeni_image_annotator/image_patcher.py
digitalsreeni_image_annotator/import_formats.py
digitalsreeni_image_annotator/main.py
digitalsreeni_image_annotator/project_details.py
digitalsreeni_image_annotator/project_search.py
digitalsreeni_image_annotator/sam_utils.py
digitalsreeni_image_annotator/slice_registration.py
digitalsreeni_image_annotator/snake_game.py
digitalsreeni_image_annotator/soft_dark_stylesheet.py
digitalsreeni_image_annotator/stack_interpolator.py
digitalsreeni_image_annotator/stack_to_slices.py
digitalsreeni_image_annotator/utils.py
digitalsreeni_image_annotator/yolo_trainer.py
digitalsreeni_image_annotator-0.8.12.dist-info/LICENSE
digitalsreeni_image_annotator-0.8.12.dist-info/METADATA
digitalsreeni_image_annotator-0.8.12.dist-info/WHEEL
digitalsreeni_image_annotator-0.8.12.dist-info/entry_points.txt
digitalsreeni_image_annotator-0.8.12.dist-info/top_level.txt
digitalsreeni_image_annotator-0.8.12.dist-info/RECORD
