Metadata-Version: 2.2
Name: digitalsreeni-image-annotator
Version: 0.8.12
Summary: A tool for annotating images using manual and automated tools, supporting multi-dimensional images and SAM2-assisted annotations
Home-page: https://github.com/bnsreenu/digitalsreeni-image-annotator
Author: Dr. Sreenivas Bhattiprolu
Author-email: digitalsreeni@gmail.com
Classifier: Development Status :: 3 - Alpha
Classifier: Intended Audience :: Science/Research
Classifier: Intended Audience :: Developers
Classifier: License :: OSI Approved :: MIT License
Classifier: Operating System :: OS Independent
Classifier: Programming Language :: Python :: 3.10
Requires-Python: >=3.10
License-File: LICENSE
Requires-Dist: PyQt5==5.15.11
Requires-Dist: numpy==2.1.3
Requires-Dist: Pillow==11.0.0
Requires-Dist: tifffile==2023.3.15
Requires-Dist: czifile==2019.7.2
Requires-Dist: opencv-python==4.10.0.84
Requires-Dist: pyyaml==6.0.2
Requires-Dist: scikit-image==0.24.0
Requires-Dist: ultralytics==8.3.27
Requires-Dist: plotly==5.24.1
Requires-Dist: shapely==2.0.6
Requires-Dist: pystackreg==0.2.8
Requires-Dist: pydicom==3.0.1
Dynamic: author
Dynamic: author-email
Dynamic: classifier
Dynamic: description
Dynamic: description-content-type
Dynamic: home-page
Dynamic: requires-dist
Dynamic: requires-python
Dynamic: summary
